{
  "id": 2025020720,
  "season": 20252026,
  "gameType": 2,
  "limitedScoring": false,
  "gameDate": "2026-01-12",
  "venue": {
    "default": "Centre Bell"
  },
  "venueLocation": {
    "default": "Montreal",
    "fr": "Montr\u00e9al"
  },
  "startTimeUTC": "2026-01-13T00:30:00Z",
  "easternUTCOffset": "-05:00",
  "venueUTCOffset": "-05:00",
  "venueTimezone": "America/Montreal",
  "periodDescriptor": {
    "number": 3,
    "periodType": "REG",
    "maxRegulationPeriods": 3
  },
  "tvBroadcasts": [
    {
      "id": 548,
      "market": "N",
      "countryCode": "CA",
      "network": "Prime",
      "sequenceNumber": 116
    },
    {
      "id": 33,
      "market": "H",
      "countryCode": "CA",
      "network": "RDS",
      "sequenceNumber": 145
    }
  ],
  "gameState": "OFF",
  "gameScheduleState": "OK",
  "awayTeam": {
    "id": 23,
    "commonName": {
      "default": "Canucks"
    },
    "abbrev": "VAN",
    "placeName": {
      "default": "Vancouver"
    },
    "placeNameWithPreposition": {
      "default": "Vancouver",
      "fr": "de Vancouver"
    },
    "score": 3,
    "sog": 23,
    "logo": "https://assets.nhle.com/logos/nhl/svg/VAN_light.svg",
    "darkLogo": "https://assets.nhle.com/logos/nhl/svg/VAN_dark.svg"
  },
  "homeTeam": {
    "id": 8,
    "commonName": {
      "default": "Canadiens"
    },
    "abbrev": "MTL",
    "placeName": {
      "default": "Montr\u00e9al"
    },
    "placeNameWithPreposition": {
      "default": "Montr\u00e9al",
      "fr": "de Montr\u00e9al"
    },
    "score": 6,
    "sog": 41,
    "logo": "https://assets.nhle.com/logos/nhl/svg/MTL_light.svg",
    "darkLogo": "https://assets.nhle.com/logos/nhl/svg/MTL_dark.svg"
  },
  "shootoutInUse": true,
  "maxPeriods": 5,
  "regPeriods": 3,
  "otInUse": true,
  "tiesInUse": false,
  "summary": {
    "scoring": [
      {
        "periodDescriptor": {
          "number": 1,
          "periodType": "REG",
          "maxRegulationPeriods": 3
        },
        "goals": [
          {
            "situationCode": "1551",
            "eventId": 301,
            "strength": "ev",
            "playerId": 8480012,
            "firstName": {
              "default": "Elias"
            },
            "lastName": {
              "default": "Pettersson"
            },
            "name": {
              "default": "E. Pettersson"
            },
            "teamAbbrev": {
              "default": "VAN"
            },
            "headshot": "https://assets.nhle.com/mugs/nhl/20252026/VAN/8480012.png",
            "highlightClipSharingUrl": "https://nhl.com/video/van-mtl-pettersson-scores-goal-against-jakub-dobes-6387628619112",
            "highlightClipSharingUrlFr": "https://nhl.com/fr/video/van-mtl-pettersson-marque-un-but-contre-jakub-dobes-6387629505112",
            "highlightClip": 6387628619112,
            "highlightClipFr": 6387629505112,
            "discreteClip": 6387628918112,
            "discreteClipFr": 6387630590112,
            "goalsToDate": 12,
            "awayScore": 1,
            "homeScore": 0,
            "leadingTeamAbbrev": {
              "default": "VAN"
            },
            "timeInPeriod": "11:53",
            "shotType": "snap",
            "goalModifier": "none",
            "assists": [
              {
                "playerId": 8481024,
                "firstName": {
                  "default": "Linus"
                },
                "lastName": {
                  "default": "Karlsson"
                },
                "name": {
                  "default": "L. Karlsson"
                },
                "assistsToDate": 10,
                "sweaterNumber": 94
              },
              {
                "playerId": 8479425,
                "firstName": {
                  "default": "Filip"
                },
                "lastName": {
                  "default": "Hronek"
                },
                "name": {
                  "default": "F. Hronek"
                },
                "assistsToDate": 24,
                "sweaterNumber": 17
              }
            ],
            "pptReplayUrl": "https://wsr.nhle.com/sprites/20252026/2025020720/ev301.json",
            "homeTeamDefendingSide": "right",
            "isHome": false
          },
          {
            "situationCode": "1451",
            "eventId": 399,
            "strength": "pp",
            "playerId": 8480865,
            "firstName": {
              "default": "Noah"
            },
            "lastName": {
              "default": "Dobson"
            },
            "name": {
              "default": "N. Dobson"
            },
            "teamAbbrev": {
              "default": "MTL"
            },
            "headshot": "https://assets.nhle.com/mugs/nhl/20252026/MTL/8480865.png",
            "highlightClipSharingUrl": "https://nhl.com/video/van-mtl-dobson-scores-ppg-against-nikita-tolopilo-6387630531112",
            "highlightClipSharingUrlFr": "https://nhl.com/fr/video/van-mtl-dobson-marque-un-but-en-a-n-contre-nikita-tolopilo-6387629030112",
            "highlightClip": 6387630531112,
            "highlightClipFr": 6387629030112,
            "discreteClip": 6387628639112,
            "discreteClipFr": 6387629033112,
            "goalsToDate": 9,
            "awayScore": 1,
            "homeScore": 1,
            "timeInPeriod": "18:13",
            "shotType": "snap",
            "goalModifier": "none",
            "assists": [
              {
                "playerId": 8480018,
                "firstName": {
                  "default": "Nick"
                },
                "lastName": {
                  "default": "Suzuki"
                },
                "name": {
                  "default": "N. Suzuki"
                },
                "assistsToDate": 35,
                "sweaterNumber": 14
              }
            ],
            "pptReplayUrl": "https://wsr.nhle.com/sprites/20252026/2025020720/ev399.json",
            "homeTeamDefendingSide": "right",
            "isHome": true
          }
        ]
      },
      {
        "periodDescriptor": {
          "number": 2,
          "periodType": "REG",
          "maxRegulationPeriods": 3
        },
        "goals": [
          {
            "situationCode": "1551",
            "eventId": 495,
            "strength": "ev",
            "playerId": 8475169,
            "firstName": {
              "default": "Evander"
            },
            "lastName": {
              "default": "Kane"
            },
            "name": {
              "default": "E. Kane"
            },
            "teamAbbrev": {
              "default": "VAN"
            },
            "headshot": "https://assets.nhle.com/mugs/nhl/20252026/VAN/8475169.png",
            "highlightClipSharingUrl": "https://nhl.com/video/van-mtl-kane-scores-goal-against-jakub-dobes-6387630454112",
            "highlightClipSharingUrlFr": "https://nhl.com/fr/video/van-mtl-kane-marque-un-but-contre-jakub-dobes-6387632004112",
            "highlightClip": 6387630454112,
            "highlightClipFr": 6387632004112,
            "discreteClip": 6387629858112,
            "discreteClipFr": 6387632799112,
            "goalsToDate": 7,
            "awayScore": 2,
            "homeScore": 1,
            "leadingTeamAbbrev": {
              "default": "VAN"
            },
            "timeInPeriod": "01:50",
            "shotType": "snap",
            "goalModifier": "none",
            "assists": [
              {
                "playerId": 8482691,
                "firstName": {
                  "default": "Aatu"
                },
                "lastName": {
                  "default": "R\u00e4ty"
                },
                "name": {
                  "default": "A. R\u00e4ty"
                },
                "assistsToDate": 9,
                "sweaterNumber": 54
              }
            ],
            "pptReplayUrl": "https://wsr.nhle.com/sprites/20252026/2025020720/ev495.json",
            "homeTeamDefendingSide": "left",
            "isHome": false
          },
          {
            "situationCode": "1551",
            "eventId": 527,
            "strength": "ev",
            "playerId": 8478851,
            "firstName": {
              "default": "Alexandre"
            },
            "lastName": {
              "default": "Carrier"
            },
            "name": {
              "default": "A. Carrier"
            },
            "teamAbbrev": {
              "default": "MTL"
            },
            "headshot": "https://assets.nhle.com/mugs/nhl/20252026/MTL/8478851.png",
            "highlightClipSharingUrl": "https://nhl.com/video/van-mtl-carrier-scores-goal-against-nikita-tolopilo-6387630918112",
            "highlightClipSharingUrlFr": "https://nhl.com/fr/video/van-mtl-carrier-marque-un-but-contre-nikita-tolopilo-6387632403112",
            "highlightClip": 6387630918112,
            "highlightClipFr": 6387632403112,
            "discreteClip": 6387632106112,
            "discreteClipFr": 6387630358112,
            "goalsToDate": 2,
            "awayScore": 2,
            "homeScore": 2,
            "timeInPeriod": "04:31",
            "shotType": "snap",
            "goalModifier": "none",
            "assists": [
              {
                "playerId": 8480018,
                "firstName": {
                  "default": "Nick"
                },
                "lastName": {
                  "default": "Suzuki"
                },
                "name": {
                  "default": "N. Suzuki"
                },
                "assistsToDate": 36,
                "sweaterNumber": 14
              },
              {
                "playerId": 8480074,
                "firstName": {
                  "default": "Alexandre"
                },
                "lastName": {
                  "default": "Texier"
                },
                "name": {
                  "default": "A. Texier"
                },
                "assistsToDate": 9,
                "sweaterNumber": 85
              }
            ],
            "pptReplayUrl": "https://wsr.nhle.com/sprites/20252026/2025020720/ev527.json",
            "homeTeamDefendingSide": "left",
            "isHome": true
          },
          {
            "situationCode": "1551",
            "eventId": 534,
            "strength": "ev",
            "playerId": 8478851,
            "firstName": {
              "default": "Alexandre"
            },
            "lastName": {
              "default": "Carrier"
            },
            "name": {
              "default": "A. Carrier"
            },
            "teamAbbrev": {
              "default": "MTL"
            },
            "headshot": "https://assets.nhle.com/mugs/nhl/20252026/MTL/8478851.png",
            "highlightClipSharingUrl": "https://nhl.com/video/van-mtl-carrier-scores-goal-against-nikita-tolopilo-6387632324112",
            "highlightClipSharingUrlFr": "https://nhl.com/fr/video/van-mtl-carrier-marque-un-but-contre-nikita-tolopilo-6387631048112",
            "highlightClip": 6387632324112,
            "highlightClipFr": 6387631048112,
            "discreteClip": 6387633511112,
            "discreteClipFr": 6387631147112,
            "goalsToDate": 3,
            "awayScore": 2,
            "homeScore": 3,
            "leadingTeamAbbrev": {
              "default": "MTL"
            },
            "timeInPeriod": "04:51",
            "shotType": "snap",
            "goalModifier": "none",
            "assists": [
              {
                "playerId": 8483515,
                "firstName": {
                  "default": "Juraj"
                },
                "lastName": {
                  "default": "Slafkovsk\u00fd"
                },
                "name": {
                  "default": "J. Slafkovsk\u00fd"
                },
                "assistsToDate": 20,
                "sweaterNumber": 20
              },
              {
                "playerId": 8484984,
                "firstName": {
                  "default": "Ivan"
                },
                "lastName": {
                  "default": "Demidov"
                },
                "name": {
                  "default": "I. Demidov"
                },
                "assistsToDate": 27,
                "sweaterNumber": 93
              }
            ],
            "pptReplayUrl": "https://wsr.nhle.com/sprites/20252026/2025020720/ev534.json",
            "homeTeamDefendingSide": "left",
            "isHome": true
          },
          {
            "situationCode": "1551",
            "eventId": 586,
            "strength": "ev",
            "playerId": 8484136,
            "firstName": {
              "default": "Max"
            },
            "lastName": {
              "default": "Sasson"
            },
            "name": {
              "default": "M. Sasson"
            },
            "teamAbbrev": {
              "default": "VAN"
            },
            "headshot": "https://assets.nhle.com/mugs/nhl/20252026/VAN/8484136.png",
            "highlightClipSharingUrl": "https://nhl.com/video/max-sasson-with-a-goal-vs-montreal-canadiens-6387632507112",
            "highlightClipSharingUrlFr": "https://nhl.com/fr/video/van-mtl-sasson-marque-un-but-contre-jakub-dobes-6387632022112",
            "highlightClip": 6387632507112,
            "highlightClipFr": 6387632022112,
            "discreteClip": 6387632119112,
            "discreteClipFr": 6387632609112,
            "goalsToDate": 9,
            "awayScore": 3,
            "homeScore": 3,
            "timeInPeriod": "09:42",
            "shotType": "snap",
            "goalModifier": "none",
            "assists": [
              {
                "playerId": 8482055,
                "firstName": {
                  "default": "Drew"
                },
                "lastName": {
                  "default": "O'Connor"
                },
                "name": {
                  "default": "D. O'Connor"
                },
                "assistsToDate": 7,
                "sweaterNumber": 18
              },
              {
                "playerId": 8480058,
                "firstName": {
                  "default": "Pierre-Olivier"
                },
                "lastName": {
                  "default": "Joseph"
                },
                "name": {
                  "default": "P. Joseph"
                },
                "assistsToDate": 2,
                "sweaterNumber": 7
              }
            ],
            "pptReplayUrl": "https://wsr.nhle.com/sprites/20252026/2025020720/ev586.json",
            "homeTeamDefendingSide": "left",
            "isHome": false
          }
        ]
      },
      {
        "periodDescriptor": {
          "number": 3,
          "periodType": "REG",
          "maxRegulationPeriods": 3
        },
        "goals": [
          {
            "situationCode": "1551",
            "eventId": 717,
            "strength": "ev",
            "playerId": 8476875,
            "firstName": {
              "default": "Mike"
            },
            "lastName": {
              "default": "Matheson"
            },
            "name": {
              "default": "M. Matheson"
            },
            "teamAbbrev": {
              "default": "MTL"
            },
            "headshot": "https://assets.nhle.com/mugs/nhl/20252026/MTL/8476875.png",
            "highlightClipSharingUrl": "https://nhl.com/video/van-mtl-matheson-scores-goal-against-nikita-tolopilo-6387635031112",
            "highlightClipSharingUrlFr": "https://nhl.com/fr/video/van-mtl-matheson-marque-un-but-contre-nikita-tolopilo-6387634433112",
            "highlightClip": 6387635031112,
            "highlightClipFr": 6387634433112,
            "discreteClip": 6387634732112,
            "discreteClipFr": 6387634737112,
            "goalsToDate": 5,
            "awayScore": 3,
            "homeScore": 4,
            "leadingTeamAbbrev": {
              "default": "MTL"
            },
            "timeInPeriod": "00:29",
            "shotType": "snap",
            "goalModifier": "none",
            "assists": [
              {
                "playerId": 8481540,
                "firstName": {
                  "default": "Cole"
                },
                "lastName": {
                  "default": "Caufield"
                },
                "name": {
                  "default": "C. Caufield"
                },
                "assistsToDate": 22,
                "sweaterNumber": 13
              },
              {
                "playerId": 8480074,
                "firstName": {
                  "default": "Alexandre"
                },
                "lastName": {
                  "default": "Texier"
                },
                "name": {
                  "default": "A. Texier"
                },
                "assistsToDate": 10,
                "sweaterNumber": 85
              }
            ],
            "pptReplayUrl": "https://wsr.nhle.com/sprites/20252026/2025020720/ev717.json",
            "homeTeamDefendingSide": "right",
            "isHome": true
          },
          {
            "situationCode": "1551",
            "eventId": 723,
            "strength": "ev",
            "playerId": 8483515,
            "firstName": {
              "default": "Juraj"
            },
            "lastName": {
              "default": "Slafkovsk\u00fd"
            },
            "name": {
              "default": "J. Slafkovsk\u00fd"
            },
            "teamAbbrev": {
              "default": "MTL"
            },
            "headshot": "https://assets.nhle.com/mugs/nhl/20252026/MTL/8483515.png",
            "highlightClipSharingUrl": "https://nhl.com/video/van-mtl-slafkovsky-scores-goal-against-nikita-tolopilo-6387632485112",
            "highlightClipSharingUrlFr": "https://nhl.com/fr/video/van-mtl-slafkovsky-marque-un-but-contre-nikita-tolopilo-6387632988112",
            "highlightClip": 6387632485112,
            "highlightClipFr": 6387632988112,
            "discreteClip": 6387634431112,
            "discreteClipFr": 6387633383112,
            "goalsToDate": 17,
            "awayScore": 3,
            "homeScore": 5,
            "leadingTeamAbbrev": {
              "default": "MTL"
            },
            "timeInPeriod": "01:07",
            "shotType": "snap",
            "goalModifier": "none",
            "assists": [
              {
                "playerId": 8484984,
                "firstName": {
                  "default": "Ivan"
                },
                "lastName": {
                  "default": "Demidov"
                },
                "name": {
                  "default": "I. Demidov"
                },
                "assistsToDate": 28,
                "sweaterNumber": 93
              },
              {
                "playerId": 8483457,
                "firstName": {
                  "default": "Lane"
                },
                "lastName": {
                  "default": "Hutson"
                },
                "name": {
                  "default": "L. Hutson"
                },
                "assistsToDate": 37,
                "sweaterNumber": 48
              }
            ],
            "pptReplayUrl": "https://wsr.nhle.com/sprites/20252026/2025020720/ev723.json",
            "homeTeamDefendingSide": "right",
            "isHome": true
          },
          {
            "situationCode": "1551",
            "eventId": 799,
            "strength": "ev",
            "playerId": 8482775,
            "firstName": {
              "default": "Oliver"
            },
            "lastName": {
              "default": "Kapanen"
            },
            "name": {
              "default": "O. Kapanen"
            },
            "teamAbbrev": {
              "default": "MTL"
            },
            "headshot": "https://assets.nhle.com/mugs/nhl/20252026/MTL/8482775.png",
            "highlightClipSharingUrl": "https://nhl.com/video/van-mtl-kapanen-scores-goal-against-nikita-tolopilo-6387635060112",
            "highlightClipSharingUrlFr": "https://nhl.com/fr/video/van-mtl-kapanen-marque-un-but-contre-nikita-tolopilo-6387636335112",
            "highlightClip": 6387635060112,
            "highlightClipFr": 6387636335112,
            "discreteClip": 6387634547112,
            "discreteClipFr": 6387634961112,
            "goalsToDate": 16,
            "awayScore": 3,
            "homeScore": 6,
            "leadingTeamAbbrev": {
              "default": "MTL"
            },
            "timeInPeriod": "06:05",
            "shotType": "snap",
            "goalModifier": "none",
            "assists": [
              {
                "playerId": 8484984,
                "firstName": {
                  "default": "Ivan"
                },
                "lastName": {
                  "default": "Demidov"
                },
                "name": {
                  "default": "I. Demidov"
                },
                "assistsToDate": 29,
                "sweaterNumber": 93
              },
              {
                "playerId": 8483515,
                "firstName": {
                  "default": "Juraj"
                },
                "lastName": {
                  "default": "Slafkovsk\u00fd"
                },
                "name": {
                  "default": "J. Slafkovsk\u00fd"
                },
                "assistsToDate": 21,
                "sweaterNumber": 20
              }
            ],
            "pptReplayUrl": "https://wsr.nhle.com/sprites/20252026/2025020720/ev799.json",
            "homeTeamDefendingSide": "right",
            "isHome": true
          }
        ]
      }
    ],
    "threeStars": [
      {
        "star": 1,
        "playerId": 8478851,
        "teamAbbrev": "MTL",
        "headshot": "https://assets.nhle.com/mugs/nhl/20252026/MTL/8478851.png",
        "name": {
          "default": "A. Carrier"
        },
        "sweaterNo": 45,
        "position": "D",
        "goals": 2,
        "assists": 0,
        "points": 2
      },
      {
        "star": 2,
        "playerId": 8483515,
        "teamAbbrev": "MTL",
        "headshot": "https://assets.nhle.com/mugs/nhl/20252026/MTL/8483515.png",
        "name": {
          "default": "J. Slafkovsk\u00fd"
        },
        "sweaterNo": 20,
        "position": "L",
        "goals": 1,
        "assists": 2,
        "points": 3
      },
      {
        "star": 3,
        "playerId": 8484984,
        "teamAbbrev": "MTL",
        "headshot": "https://assets.nhle.com/mugs/nhl/20252026/MTL/8484984.png",
        "name": {
          "default": "I. Demidov"
        },
        "sweaterNo": 93,
        "position": "R",
        "goals": 0,
        "assists": 3,
        "points": 3
      }
    ],
    "penalties": [
      {
        "periodDescriptor": {
          "number": 1,
          "periodType": "REG",
          "maxRegulationPeriods": 3
        },
        "penalties": [
          {
            "timeInPeriod": "18:09",
            "type": "MIN",
            "duration": 2,
            "committedByPlayer": {
              "firstName": {
                "default": "Brock"
              },
              "lastName": {
                "default": "Boeser"
              },
              "sweaterNumber": 6
            },
            "teamAbbrev": {
              "default": "VAN"
            },
            "drawnBy": {
              "firstName": {
                "default": "Phillip"
              },
              "lastName": {
                "default": "Danault"
              },
              "sweaterNumber": 24
            },
            "descKey": "hooking"
          }
        ]
      },
      {
        "periodDescriptor": {
          "number": 2,
          "periodType": "REG",
          "maxRegulationPeriods": 3
        },
        "penalties": []
      },
      {
        "periodDescriptor": {
          "number": 3,
          "periodType": "REG",
          "maxRegulationPeriods": 3
        },
        "penalties": [
          {
            "timeInPeriod": "10:19",
            "type": "MIN",
            "duration": 2,
            "committedByPlayer": {
              "firstName": {
                "default": "Alexandre"
              },
              "lastName": {
                "default": "Carrier"
              },
              "sweaterNumber": 45
            },
            "teamAbbrev": {
              "default": "MTL"
            },
            "drawnBy": {
              "firstName": {
                "default": "Liam"
              },
              "lastName": {
                "default": "Ohgren",
                "cs": "\u00d6hgren",
                "fi": "\u00d6hgren",
                "sk": "\u00d6hgren",
                "sv": "\u00d6hgren"
              },
              "sweaterNumber": 92
            },
            "descKey": "cross-checking"
          },
          {
            "timeInPeriod": "17:48",
            "type": "MIN",
            "duration": 2,
            "committedByPlayer": {
              "firstName": {
                "default": "Noah"
              },
              "lastName": {
                "default": "Dobson"
              },
              "sweaterNumber": 53
            },
            "teamAbbrev": {
              "default": "MTL"
            },
            "drawnBy": {
              "firstName": {
                "default": "Nils"
              },
              "lastName": {
                "default": "Hoglander",
                "cs": "H\u00f6glander",
                "fi": "H\u00f6glander",
                "sk": "H\u00f6glander",
                "sv": "H\u00f6glander"
              },
              "sweaterNumber": 21
            },
            "descKey": "hooking"
          }
        ]
      }
    ]
  },
  "clock": {
    "timeRemaining": "00:00",
    "secondsRemaining": 0,
    "running": false,
    "inIntermission": false
  }
}