{
  "id": 2025020730,
  "season": 20252026,
  "gameType": 2,
  "limitedScoring": false,
  "gameDate": "2026-01-13",
  "venue": {
    "default": "Enterprise Center"
  },
  "venueLocation": {
    "default": "St. Louis"
  },
  "startTimeUTC": "2026-01-14T00:30:00Z",
  "easternUTCOffset": "-05:00",
  "venueUTCOffset": "-06:00",
  "venueTimezone": "US/Central",
  "periodDescriptor": {
    "number": 3,
    "periodType": "REG",
    "maxRegulationPeriods": 3
  },
  "tvBroadcasts": [
    {
      "id": 329,
      "market": "N",
      "countryCode": "US",
      "network": "ESPN+",
      "sequenceNumber": 16
    },
    {
      "id": 391,
      "market": "N",
      "countryCode": "US",
      "network": "HULU",
      "sequenceNumber": 17
    }
  ],
  "gameState": "OFF",
  "gameScheduleState": "OK",
  "awayTeam": {
    "id": 12,
    "commonName": {
      "default": "Hurricanes"
    },
    "abbrev": "CAR",
    "placeName": {
      "default": "Carolina",
      "fr": "Caroline"
    },
    "placeNameWithPreposition": {
      "default": "Carolina",
      "fr": "de la Caroline"
    },
    "score": 0,
    "sog": 33,
    "logo": "https://assets.nhle.com/logos/nhl/svg/CAR_light.svg",
    "darkLogo": "https://assets.nhle.com/logos/nhl/svg/CAR_dark.svg"
  },
  "homeTeam": {
    "id": 19,
    "commonName": {
      "default": "Blues"
    },
    "abbrev": "STL",
    "placeName": {
      "default": "St. Louis"
    },
    "placeNameWithPreposition": {
      "default": "St. Louis",
      "fr": "de St. Louis"
    },
    "score": 3,
    "sog": 31,
    "logo": "https://assets.nhle.com/logos/nhl/svg/STL_light.svg?season=20252026",
    "darkLogo": "https://assets.nhle.com/logos/nhl/svg/STL_dark.svg?season=20252026"
  },
  "shootoutInUse": true,
  "maxPeriods": 5,
  "regPeriods": 3,
  "otInUse": true,
  "tiesInUse": false,
  "summary": {
    "scoring": [
      {
        "periodDescriptor": {
          "number": 1,
          "periodType": "REG",
          "maxRegulationPeriods": 3
        },
        "goals": []
      },
      {
        "periodDescriptor": {
          "number": 2,
          "periodType": "REG",
          "maxRegulationPeriods": 3
        },
        "goals": [
          {
            "situationCode": "1541",
            "eventId": 522,
            "strength": "sh",
            "playerId": 8475760,
            "firstName": {
              "default": "Nick"
            },
            "lastName": {
              "default": "Bjugstad"
            },
            "name": {
              "default": "N. Bjugstad"
            },
            "teamAbbrev": {
              "default": "STL"
            },
            "headshot": "https://assets.nhle.com/mugs/nhl/20252026/STL/8475760.png",
            "highlightClipSharingUrl": "https://nhl.com/video/nick-bjugstad-with-a-shorthanded-goal-vs-carolina-hurricanes-6387687824112",
            "highlightClipSharingUrlFr": "https://nhl.com/fr/video/nick-bjugstad-with-a-shorthanded-goal-vs-les-hurricanes-de-la-caroline-6387689055112",
            "highlightClip": 6387687824112,
            "highlightClipFr": 6387689055112,
            "discreteClip": 6387688565112,
            "discreteClipFr": 6387688285112,
            "goalsToDate": 5,
            "awayScore": 0,
            "homeScore": 1,
            "leadingTeamAbbrev": {
              "default": "STL"
            },
            "timeInPeriod": "03:09",
            "shotType": "wrist",
            "goalModifier": "none",
            "assists": [
              {
                "playerId": 8484230,
                "firstName": {
                  "default": "Otto"
                },
                "lastName": {
                  "default": "Stenberg"
                },
                "name": {
                  "default": "O. Stenberg"
                },
                "assistsToDate": 6,
                "sweaterNumber": 28
              },
              {
                "playerId": 8475753,
                "firstName": {
                  "default": "Justin"
                },
                "lastName": {
                  "default": "Faulk"
                },
                "name": {
                  "default": "J. Faulk"
                },
                "assistsToDate": 11,
                "sweaterNumber": 72
              }
            ],
            "pptReplayUrl": "https://wsr.nhle.com/sprites/20252026/2025020730/ev522.json",
            "homeTeamDefendingSide": "right",
            "isHome": true
          },
          {
            "situationCode": "1551",
            "eventId": 605,
            "strength": "ev",
            "playerId": 8484164,
            "firstName": {
              "default": "Dalibor"
            },
            "lastName": {
              "default": "Dvorsky"
            },
            "name": {
              "default": "D. Dvorsky"
            },
            "teamAbbrev": {
              "default": "STL"
            },
            "headshot": "https://assets.nhle.com/mugs/nhl/20252026/STL/8484164.png",
            "highlightClipSharingUrl": "https://nhl.com/video/car-stl-dvorsky-scores-goal-against-brandon-bussi-6387688202112",
            "highlightClipSharingUrlFr": "https://nhl.com/fr/video/car-stl-dvorsky-marque-un-but-contre-brandon-bussi-6387688873112",
            "highlightClip": 6387688202112,
            "highlightClipFr": 6387688873112,
            "discreteClip": 6387688115112,
            "discreteClipFr": 6387689766112,
            "goalsToDate": 7,
            "awayScore": 0,
            "homeScore": 2,
            "leadingTeamAbbrev": {
              "default": "STL"
            },
            "timeInPeriod": "09:45",
            "shotType": "snap",
            "goalModifier": "none",
            "assists": [
              {
                "playerId": 8482089,
                "firstName": {
                  "default": "Jake"
                },
                "lastName": {
                  "default": "Neighbours"
                },
                "name": {
                  "default": "J. Neighbours"
                },
                "assistsToDate": 8,
                "sweaterNumber": 63
              },
              {
                "playerId": 8481006,
                "firstName": {
                  "default": "Tyler"
                },
                "lastName": {
                  "default": "Tucker"
                },
                "name": {
                  "default": "T. Tucker"
                },
                "assistsToDate": 7,
                "sweaterNumber": 75
              }
            ],
            "pptReplayUrl": "https://wsr.nhle.com/sprites/20252026/2025020730/ev605.json",
            "homeTeamDefendingSide": "right",
            "isHome": true
          },
          {
            "situationCode": "1451",
            "eventId": 648,
            "strength": "pp",
            "playerId": 8483516,
            "firstName": {
              "default": "Jimmy"
            },
            "lastName": {
              "default": "Snuggerud"
            },
            "name": {
              "default": "J. Snuggerud"
            },
            "teamAbbrev": {
              "default": "STL"
            },
            "headshot": "https://assets.nhle.com/mugs/nhl/20252026/STL/8483516.png",
            "highlightClipSharingUrl": "https://nhl.com/video/car-stl-snuggerud-scores-ppg-against-brandon-bussi-6387687406112",
            "highlightClipSharingUrlFr": "https://nhl.com/fr/video/car-stl-snuggerud-marque-un-but-en-a-n-contre-brandon-bussi-6387688810112",
            "highlightClip": 6387687406112,
            "highlightClipFr": 6387688810112,
            "discreteClip": 6387688883112,
            "discreteClipFr": 6387688010112,
            "goalsToDate": 7,
            "awayScore": 0,
            "homeScore": 3,
            "leadingTeamAbbrev": {
              "default": "STL"
            },
            "timeInPeriod": "12:49",
            "shotType": "wrist",
            "goalModifier": "none",
            "assists": [
              {
                "playerId": 8479385,
                "firstName": {
                  "default": "Jordan"
                },
                "lastName": {
                  "default": "Kyrou"
                },
                "name": {
                  "default": "J. Kyrou"
                },
                "assistsToDate": 11,
                "sweaterNumber": 25
              },
              {
                "playerId": 8475170,
                "firstName": {
                  "default": "Brayden"
                },
                "lastName": {
                  "default": "Schenn"
                },
                "name": {
                  "default": "B. Schenn"
                },
                "assistsToDate": 10,
                "sweaterNumber": 10
              }
            ],
            "pptReplayUrl": "https://wsr.nhle.com/sprites/20252026/2025020730/ev648.json",
            "homeTeamDefendingSide": "right",
            "isHome": true
          }
        ]
      },
      {
        "periodDescriptor": {
          "number": 3,
          "periodType": "REG",
          "maxRegulationPeriods": 3
        },
        "goals": []
      }
    ],
    "threeStars": [
      {
        "star": 1,
        "playerId": 8480981,
        "teamAbbrev": "STL",
        "headshot": "https://assets.nhle.com/mugs/nhl/20252026/STL/8480981.png",
        "name": {
          "default": "J. Hofer"
        },
        "sweaterNo": 30,
        "position": "G",
        "goalsAgainstAverage": 0.0,
        "savePctg": 1.0
      },
      {
        "star": 2,
        "playerId": 8475760,
        "teamAbbrev": "STL",
        "headshot": "https://assets.nhle.com/mugs/nhl/20252026/STL/8475760.png",
        "name": {
          "default": "N. Bjugstad"
        },
        "sweaterNo": 77,
        "position": "C",
        "goals": 1,
        "assists": 0,
        "points": 1
      },
      {
        "star": 3,
        "playerId": 8475170,
        "teamAbbrev": "STL",
        "headshot": "https://assets.nhle.com/mugs/nhl/20252026/STL/8475170.png",
        "name": {
          "default": "B. Schenn"
        },
        "sweaterNo": 10,
        "position": "C",
        "goals": 0,
        "assists": 1,
        "points": 1
      }
    ],
    "penalties": [
      {
        "periodDescriptor": {
          "number": 1,
          "periodType": "REG",
          "maxRegulationPeriods": 3
        },
        "penalties": [
          {
            "timeInPeriod": "05:31",
            "type": "MIN",
            "duration": 2,
            "committedByPlayer": {
              "firstName": {
                "default": "Brayden"
              },
              "lastName": {
                "default": "Schenn"
              },
              "sweaterNumber": 10
            },
            "teamAbbrev": {
              "default": "STL"
            },
            "drawnBy": {
              "firstName": {
                "default": "Andrei",
                "cs": "Andrej",
                "sk": "Andrej"
              },
              "lastName": {
                "default": "Svechnikov",
                "cs": "Sve\u010dnikov",
                "fi": "Svetshnikov",
                "sk": "Sve\u010dnikov"
              },
              "sweaterNumber": 37
            },
            "descKey": "holding"
          }
        ]
      },
      {
        "periodDescriptor": {
          "number": 2,
          "periodType": "REG",
          "maxRegulationPeriods": 3
        },
        "penalties": [
          {
            "timeInPeriod": "01:42",
            "type": "MIN",
            "duration": 2,
            "committedByPlayer": {
              "firstName": {
                "default": "Logan"
              },
              "lastName": {
                "default": "Mailloux"
              },
              "sweaterNumber": 23
            },
            "teamAbbrev": {
              "default": "STL"
            },
            "drawnBy": {
              "firstName": {
                "default": "Taylor"
              },
              "lastName": {
                "default": "Hall"
              },
              "sweaterNumber": 71
            },
            "descKey": "tripping"
          },
          {
            "timeInPeriod": "12:07",
            "type": "MIN",
            "duration": 2,
            "committedByPlayer": {
              "firstName": {
                "default": "Sebastian"
              },
              "lastName": {
                "default": "Aho"
              },
              "sweaterNumber": 20
            },
            "teamAbbrev": {
              "default": "CAR"
            },
            "drawnBy": {
              "firstName": {
                "default": "Nick"
              },
              "lastName": {
                "default": "Bjugstad"
              },
              "sweaterNumber": 77
            },
            "descKey": "interference"
          },
          {
            "timeInPeriod": "18:00",
            "type": "MIN",
            "duration": 2,
            "committedByPlayer": {
              "firstName": {
                "default": "Mike"
              },
              "lastName": {
                "default": "Reilly"
              },
              "sweaterNumber": 6
            },
            "teamAbbrev": {
              "default": "CAR"
            },
            "descKey": "delaying-game-puck-over-glass"
          }
        ]
      },
      {
        "periodDescriptor": {
          "number": 3,
          "periodType": "REG",
          "maxRegulationPeriods": 3
        },
        "penalties": [
          {
            "timeInPeriod": "09:39",
            "type": "MIN",
            "duration": 2,
            "committedByPlayer": {
              "firstName": {
                "default": "Tyler"
              },
              "lastName": {
                "default": "Tucker"
              },
              "sweaterNumber": 75
            },
            "teamAbbrev": {
              "default": "STL"
            },
            "drawnBy": {
              "firstName": {
                "default": "Taylor"
              },
              "lastName": {
                "default": "Hall"
              },
              "sweaterNumber": 71
            },
            "descKey": "hooking"
          },
          {
            "timeInPeriod": "13:38",
            "type": "MIN",
            "duration": 2,
            "committedByPlayer": {
              "firstName": {
                "default": "Sean"
              },
              "lastName": {
                "default": "Walker"
              },
              "sweaterNumber": 26
            },
            "teamAbbrev": {
              "default": "CAR"
            },
            "drawnBy": {
              "firstName": {
                "default": "Jimmy"
              },
              "lastName": {
                "default": "Snuggerud"
              },
              "sweaterNumber": 21
            },
            "descKey": "holding"
          }
        ]
      }
    ]
  },
  "clock": {
    "timeRemaining": "00:00",
    "secondsRemaining": 0,
    "running": false,
    "inIntermission": false
  }
}